screamer.libs/libstdc++-496613c0.so.6.0.32
screamer.libs/libgcc_s-a3a07607.so.1
screamer-0.1.46.dist-info/RECORD
screamer-0.1.46.dist-info/METADATA
screamer-0.1.46.dist-info/WHEEL
screamer-0.1.46.dist-info/licenses/LICENSE
screamer/screamer_bindings.cpython-311-x86_64-linux-musl.so
screamer/__init__.py
