Metadata-Version: 2.1
Name: screamer
Version: 0.1.46
Summary: Screamingly fast financial technical indicators with C++ performance and Python simplicity, built for both time series analysis and real-time, event-driven streaming.
Keywords: streaming,indicators,real-time,algorithmic,trading,low-latency
Author-Email: Thijs van den Berg <thijs@sitmo.com>, Mohammadjavad Vakili <mohammadjavad.vakili@gmail.com>
Maintainer-Email: Thijs van den Berg <thijs@sitmo.com>, Mohammadjavad Vakili <mohammadjavad.vakili@gmail.com>
License: MIT License
Classifier: Development Status :: 4 - Beta
Classifier: Intended Audience :: Developers
Classifier: Intended Audience :: Financial and Insurance Industry
Classifier: Topic :: Software Development :: Libraries :: Python Modules
Classifier: Topic :: Scientific/Engineering :: Information Analysis
Classifier: License :: OSI Approved :: MIT License
Classifier: Programming Language :: Python :: 3
Classifier: Programming Language :: Python :: 3.9
Classifier: Programming Language :: Python :: 3.10
Classifier: Programming Language :: Python :: 3.11
Classifier: Programming Language :: C++
Classifier: Operating System :: OS Independent
Project-URL: Homepage, https://github.com/quantfinlib/screamer
Project-URL: Documentation, https://screamer.readthedocs.io/en/latest/
Project-URL: Repository, https://github.com/quantfinlib/screamer.git
Project-URL: Issues, https://github.com/quantfinlib/screamer/issues
Project-URL: Changelog, https://github.com/quantfinlib/screamer/blob/master/CHANGELOG.md
Requires-Python: >=3.9
Requires-Dist: pybind11>=2.9
